django_agenda/__init__.py
django_agenda/apps.py
django_agenda/models.py
django_agenda/runtests.py
django_agenda/signals.py
django_agenda/time_span.py
django_agenda/management/__init__.py
django_agenda/management/commands/__init__.py
django_agenda/management/commands/clear_occurrences.py
django_agenda/management/commands/clear_old_slots.py
django_agenda/management/commands/recreate_time_slots.py
django_agenda/migrations/0001_initial.py
django_agenda/migrations/0002_index.py
django_agenda/migrations/0003_padding.py
django_agenda/migrations/0004_rewrite.py
django_agenda/migrations/__init__.py
tests/__init__.py
tests/admin.py
tests/apps.py
tests/demo_settings.py
tests/migrate_settings.py
tests/models.py
tests/root_urls.py
tests/settings.py
tests/signals.py
tests/test_availabilities.py
tests/test_booking.py
tests/test_generation.py
tests/test_occurences.py
tests/urls.py
tests/views.py
django_agenda-0.7.2.dist-info/AUTHORS
django_agenda-0.7.2.dist-info/LICENSE.rst
django_agenda-0.7.2.dist-info/METADATA
django_agenda-0.7.2.dist-info/WHEEL
django_agenda-0.7.2.dist-info/top_level.txt
django_agenda-0.7.2.dist-info/RECORD
