Metadata-Version: 2.1
Name: django-agenda
Version: 0.7.2
Summary: A scheduling app for Django
Home-page: https://gitlab.com/alantrick/django-agenda
Author: Alan Trick
Author-email: me@alantrick.ca
License: LGPL3+
Project-URL: Bug Tracker, https://gitlab.com/alantrick/django-agenda/issues
Project-URL: Documentation, https://alantrick.gitlab.io/django-agenda/
Project-URL: Source Code, https://gitlab.com/alantrick/django-agenda
Keywords: scheduling,calendar,availability
Platform: UNKNOWN
Classifier: Development Status :: 2 - Pre-Alpha
Classifier: Environment :: Web Environment
Classifier: Framework :: Django
Classifier: Intended Audience :: Developers
Classifier: License :: OSI Approved :: GNU Lesser General Public License v3 or later (LGPLv3+)
Classifier: Operating System :: OS Independent
Classifier: Programming Language :: Python
Classifier: Programming Language :: Python :: 3.8
Classifier: Framework :: Django
Classifier: Framework :: Django :: 1.11
Classifier: Framework :: Django :: 2.1
Classifier: Framework :: Django :: 2.2
Classifier: Framework :: Django :: 3.0
Classifier: Framework :: Django :: 3.1
Classifier: Topic :: Utilities
Classifier: Topic :: Office/Business :: Scheduling
Requires-Python: >=3.8
Requires-Dist: Django (>=1.11)
Requires-Dist: django-recurrence
Requires-Dist: django-timezone-field
Requires-Dist: pytz
Provides-Extra: docs
Requires-Dist: sphinx ; extra == 'docs'
Requires-Dist: sphinx-rtd-theme ; extra == 'docs'
Provides-Extra: test
Requires-Dist: pytest ; extra == 'test'
Requires-Dist: pytest-cov ; extra == 'test'
Requires-Dist: pytest-django ; extra == 'test'
Requires-Dist: pytest-pythonpath ; extra == 'test'
Requires-Dist: pyyaml ; extra == 'test'
Requires-Dist: tox ; extra == 'test'
